[
    {
        "name" : "Coursera",
        "domain" : "Mooc",
        "img" : "Coursera.JPG",
        "link" : "https://www.coursera.org/"
    },
    {
        "name" : "Developpez.com",
        "domain" : "Mooc",
        "img" : "Developez.JPG",
        "link" : "https://www.developpez.com/"
    },
    {
        "name" : "Openclassrooms",
        "domain" : "Mooc",
        "img" : "Openclassrooms.JPG",
        "link" : "https://openclassrooms.com/"
    },
    {
        "name" : "Stackoverflow",
        "domain" : "Coding questions and answers",
        "img" : "Stackoverflow.JPG",
        "link" : "https://stackoverflow.com/"
    },
    {
        "name" : "w3schools",
        "domain" : "Tutorials",
        "img" : "w3schools.JPG",
        "link" : "https://www.w3schools.com/"
    },
    {
        "name" : "wikipedia",
        "domain" : "Encyclopedia",
        "img" : "wikipedia.JPG",
        "link" : "https://www.wikipedia.org/"
    }
]